my_package/__init__.py
my_package/my_functions.py
my_package/version.py
frgfm_package-0.1.0.dist-info/LICENSE
frgfm_package-0.1.0.dist-info/METADATA
frgfm_package-0.1.0.dist-info/WHEEL
frgfm_package-0.1.0.dist-info/top_level.txt
frgfm_package-0.1.0.dist-info/zip-safe
frgfm_package-0.1.0.dist-info/RECORD
